dinglehopper/__init__.py
dinglehopper/align.py
dinglehopper/character_error_rate.py
dinglehopper/cli.py
dinglehopper/cli_extract.py
dinglehopper/cli_line_dirs.py
dinglehopper/cli_summarize.py
dinglehopper/config.py
dinglehopper/edit_distance.py
dinglehopper/extracted_text.py
dinglehopper/ocr_files.py
dinglehopper/ocrd-tool.json
dinglehopper/ocrd_cli.py
dinglehopper/word_error_rate.py
dinglehopper/templates/report.html.j2
dinglehopper/templates/report.html.js
dinglehopper/templates/report.json.j2
dinglehopper/templates/summary.html.j2
dinglehopper/templates/summary.json.j2
dinglehopper/tests/__init__.py
dinglehopper/tests/extracted_text_test.py
dinglehopper/tests/test_align.py
dinglehopper/tests/test_character_error_rate.py
dinglehopper/tests/test_edit_distance.py
dinglehopper/tests/test_editops.py
dinglehopper/tests/test_integ_align.py
dinglehopper/tests/test_integ_bigger_texts.py
dinglehopper/tests/test_integ_character_error_rate_ocr.py
dinglehopper/tests/test_integ_cli_dir.py
dinglehopper/tests/test_integ_cli_line_dirs.py
dinglehopper/tests/test_integ_cli_valid_report.py
dinglehopper/tests/test_integ_differences.py
dinglehopper/tests/test_integ_edit_distance_ocr.py
dinglehopper/tests/test_integ_empty_files.py
dinglehopper/tests/test_integ_ocrd_cli.py
dinglehopper/tests/test_integ_summarize.py
dinglehopper/tests/test_integ_table_extraction.py
dinglehopper/tests/test_integ_word_error_rate_ocr.py
dinglehopper/tests/test_line_dirs.py
dinglehopper/tests/test_ocr_files.py
dinglehopper/tests/test_word_error_rate.py
dinglehopper/tests/util.py
dinglehopper-0.11.0.dist-info/licenses/LICENSE
dinglehopper-0.11.0.dist-info/METADATA
dinglehopper-0.11.0.dist-info/WHEEL
dinglehopper-0.11.0.dist-info/entry_points.txt
dinglehopper-0.11.0.dist-info/top_level.txt
dinglehopper-0.11.0.dist-info/RECORD
