Metadata-Version: 2.4
Name: dinglehopper
Version: 0.11.0
Summary: An OCR evaluation tool
Author-email: Mike Gerber <mike.gerber@sbb.spk-berlin.de>, The QURATOR SPK Team <qurator@sbb.spk-berlin.de>
License:                                  Apache License
Project-URL: Homepage, https://github.com/qurator-spk/dinglehopper
Project-URL: Repository, https://github.com/qurator-spk/dinglehopper.git
Keywords: qurator,ocr,evaluation,ocr-d
Classifier: Development Status :: 5 - Production/Stable
Classifier: Environment :: Console
Classifier: Intended Audience :: Science/Research
Classifier: Intended Audience :: Other Audience
Classifier: License :: OSI Approved :: Apache Software License
Classifier: Programming Language :: Python :: 3
Classifier: Programming Language :: Python :: 3 :: Only
Classifier: Topic :: Scientific/Engineering :: Information Analysis
Classifier: Topic :: Text Processing
Requires-Python: >=3.8
License-File: LICENSE
Requires-Dist: click
Requires-Dist: jinja2
Requires-Dist: lxml
Requires-Dist: uniseg>=0.8.0
Requires-Dist: numpy
Requires-Dist: colorama
Requires-Dist: MarkupSafe
Requires-Dist: ocrd>=3.3.0
Requires-Dist: attrs
Requires-Dist: multimethod>=1.3
Requires-Dist: tqdm
Requires-Dist: rapidfuzz>=2.7.0
Requires-Dist: chardet
Requires-Dist: importlib_resources
Provides-Extra: dev
Requires-Dist: pytest; extra == "dev"
Requires-Dist: pytest-cov; extra == "dev"
Requires-Dist: black; extra == "dev"
Requires-Dist: pre-commit; extra == "dev"
Requires-Dist: ruff; extra == "dev"
Requires-Dist: pytest-ruff; extra == "dev"
Requires-Dist: mypy; extra == "dev"
Requires-Dist: types-lxml; extra == "dev"
Requires-Dist: types-setuptools; extra == "dev"
Requires-Dist: pytest-mypy; extra == "dev"
Requires-Dist: liccheck; extra == "dev"
Dynamic: license-file
